<mesh>
    <submeshes>
        <submesh material="/global/plants/trees/gnarly" usesharedvertices="false" use32bitindexes="false" operationtype="triangle_list">
            <faces count="48">
                <face v1="0" v2="1" v3="2" />
                <face v1="0" v2="3" v3="1" />
                <face v1="3" v2="4" v3="1" />
                <face v1="3" v2="5" v3="4" />
                <face v1="6" v2="7" v3="8" />
                <face v1="6" v2="9" v3="7" />
                <face v1="9" v2="10" v3="7" />
                <face v1="9" v2="11" v3="10" />
                <face v1="11" v2="12" v3="10" />
                <face v1="11" v2="13" v3="12" />
                <face v1="13" v2="14" v3="12" />
                <face v1="13" v2="15" v3="14" />
                <face v1="16" v2="17" v3="18" />
                <face v1="16" v2="19" v3="17" />
                <face v1="19" v2="2" v3="17" />
                <face v1="19" v2="0" v3="2" />
                <face v1="20" v2="21" v3="22" />
                <face v1="20" v2="23" v3="21" />
                <face v1="23" v2="24" v3="21" />
                <face v1="23" v2="25" v3="24" />
                <face v1="26" v2="27" v3="28" />
                <face v1="26" v2="29" v3="27" />
                <face v1="29" v2="30" v3="27" />
                <face v1="29" v2="31" v3="30" />
                <face v1="31" v2="32" v3="30" />
                <face v1="31" v2="33" v3="32" />
                <face v1="33" v2="34" v3="32" />
                <face v1="33" v2="35" v3="34" />
                <face v1="36" v2="37" v3="38" />
                <face v1="36" v2="39" v3="37" />
                <face v1="39" v2="22" v3="37" />
                <face v1="39" v2="20" v3="22" />
                <face v1="22" v2="40" v3="41" />
                <face v1="22" v2="21" v3="40" />
                <face v1="21" v2="42" v3="40" />
                <face v1="21" v2="24" v3="42" />
                <face v1="28" v2="43" v3="44" />
                <face v1="28" v2="27" v3="43" />
                <face v1="27" v2="45" v3="43" />
                <face v1="27" v2="30" v3="45" />
                <face v1="30" v2="46" v3="45" />
                <face v1="30" v2="32" v3="46" />
                <face v1="32" v2="47" v3="46" />
                <face v1="32" v2="34" v3="47" />
                <face v1="38" v2="48" v3="49" />
                <face v1="38" v2="37" v3="48" />
                <face v1="37" v2="41" v3="48" />
                <face v1="37" v2="22" v3="41" />
            </faces>
            <geometry vertexcount="50">
                <vertexbuffer positions="true" normals="true" texture_coord_dimensions_0="2" tangents="true" texture_coords="1">
                    <vertex>
                        <position x="9.8122" y="0" z="-0.55068" />
                        <normal x="0.990517" y="0.0130992" z="-0.136762" />
                        <texcoord u="0.0628455" v="0.500511" />
                        <tangent x="-0.136774" y="-1.23352e-07" z="-0.990602" />
                    </vertex>
                    <vertex>
                        <position x="6.33818" y="63.298" z="-6.91204" />
                        <normal x="0.707064" y="0.0106692" z="-0.707069" />
                        <texcoord u="0.0927492" v="0.313177" />
                        <tangent x="-0.707097" y="-0.0014733" z="-0.707115" />
                    </vertex>
                    <vertex>
                        <position x="8.97609" y="63.298" z="-0.543541" />
                        <normal x="0.999943" y="0.010671" z="-3.20963e-06" />
                        <texcoord u="0.0628455" v="0.313177" />
                        <tangent x="1.25278e-05" y="-0.00147355" z="-0.999999" />
                    </vertex>
                    <vertex>
                        <position x="6.92939" y="0" z="-7.51039" />
                        <normal x="0.603696" y="0.0131737" z="-0.797106" />
                        <texcoord u="0.0927492" v="0.500511" />
                        <tangent x="-0.797175" y="-1.08117e-07" z="-0.603748" />
                    </vertex>
                    <vertex>
                        <position x="-0.0303196" y="63.298" z="-9.54995" />
                        <normal x="-3.36017e-06" y="0.0106783" z="-0.999943" />
                        <texcoord u="0.122642" v="0.313177" />
                        <tangent x="-0.99999" y="-0.00442301" z="-4.38456e-05" />
                    </vertex>
                    <vertex>
                        <position x="-0.0303196" y="0" z="-10.3932" />
                        <normal x="-0.136762" y="0.0131955" z="-0.990516" />
                        <texcoord u="0.122642" v="0.500511" />
                        <tangent x="-0.990587" y="-0.00772885" z="0.136669" />
                    </vertex>
                    <vertex>
                        <position x="-0.0303196" y="0" z="-10.3932" />
                        <normal x="-0.136762" y="0.0131955" z="-0.990516" />
                        <texcoord u="0.00308991" v="0.500474" />
                        <tangent x="-0.99059" y="0.00344642" z="0.136818" />
                    </vertex>
                    <vertex>
                        <position x="-6.39882" y="63.298" z="-6.91204" />
                        <normal x="-0.707069" y="0.010693" z="-0.707064" />
                        <texcoord u="0.0329779" v="0.313161" />
                        <tangent x="-0.707115" y="-0.0014763" z="0.707097" />
                    </vertex>
                    <vertex>
                        <position x="-0.0303196" y="63.298" z="-9.54995" />
                        <normal x="-3.36017e-06" y="0.0106783" z="-0.999943" />
                        <texcoord u="0.00308991" v="0.313161" />
                        <tangent x="-0.99999" y="0.00442282" z="5.05642e-05" />
                    </vertex>
                    <vertex>
                        <position x="-6.99003" y="0" z="-7.51039" />
                        <normal x="-0.797106" y="0.0131519" z="-0.603696" />
                        <texcoord u="0.0329779" v="0.500474" />
                        <tangent x="-0.603748" y="3.32624e-08" z="0.797175" />
                    </vertex>
                    <vertex>
                        <position x="-9.03673" y="63.298" z="-0.54354" />
                        <normal x="-0.999943" y="0.0107047" z="3.31716e-06" />
                        <texcoord u="0.0628779" v="0.313161" />
                        <tangent x="-1.24172e-05" y="-0.00147791" z="0.999999" />
                    </vertex>
                    <vertex>
                        <position x="-9.87284" y="0" z="-0.550679" />
                        <normal x="-0.990518" y="0.0130684" z="0.136762" />
                        <texcoord u="0.0628779" v="0.500474" />
                        <tangent x="0.136774" y="2.54117e-08" z="0.990602" />
                    </vertex>
                    <vertex>
                        <position x="-6.39881" y="63.298" z="5.82496" />
                        <normal x="-0.707064" y="0.0107066" z="0.707069" />
                        <texcoord u="0.0927633" v="0.313161" />
                        <tangent x="0.707097" y="-0.00147817" z="0.707115" />
                    </vertex>
                    <vertex>
                        <position x="-6.99003" y="0" z="6.40903" />
                        <normal x="-0.603697" y="0.0129939" z="0.797108" />
                        <texcoord u="0.0927633" v="0.500474" />
                        <tangent x="0.797175" y="2.68967e-08" z="0.603748" />
                    </vertex>
                    <vertex>
                        <position x="-0.030318" y="63.298" z="8.46287" />
                        <normal x="3.16125e-06" y="0.0106974" z="0.999943" />
                        <texcoord u="0.12266" v="0.313161" />
                        <tangent x="0.99999" y="-0.00443071" z="4.40422e-05" />
                    </vertex>
                    <vertex>
                        <position x="-0.0303179" y="0" z="9.29184" />
                        <normal x="0.136762" y="0.0129721" z="0.990519" />
                        <texcoord u="0.12266" v="0.500474" />
                        <tangent x="0.990587" y="-0.00759802" z="-0.136672" />
                    </vertex>
                    <vertex>
                        <position x="-0.0303179" y="0" z="9.29184" />
                        <normal x="0.136762" y="0.0129721" z="0.990519" />
                        <texcoord u="0.00308702" v="0.500511" />
                        <tangent x="0.990591" y="0.0033879" z="-0.136816" />
                    </vertex>
                    <vertex>
                        <position x="6.33818" y="63.298" z="5.82495" />
                        <normal x="0.707069" y="0.0106827" z="0.707064" />
                        <texcoord u="0.0329562" v="0.313177" />
                        <tangent x="0.707115" y="-0.00147516" z="-0.707097" />
                    </vertex>
                    <vertex>
                        <position x="-0.030318" y="63.298" z="8.46287" />
                        <normal x="3.16125e-06" y="0.0106974" z="0.999943" />
                        <texcoord u="0.00308702" v="0.313177" />
                        <tangent x="0.99999" y="0.00443032" z="-5.03609e-05" />
                    </vertex>
                    <vertex>
                        <position x="6.92939" y="0" z="6.40903" />
                        <normal x="0.797108" y="0.0130157" z="0.603697" />
                        <texcoord u="0.0329562" v="0.500511" />
                        <tangent x="0.603748" y="-1.15158e-07" z="-0.797175" />
                    </vertex>
                    <vertex>
                        <position x="8.97609" y="63.298" z="-0.543541" />
                        <normal x="0.999943" y="0.010671" z="-3.20963e-06" />
                        <texcoord u="0.0628455" v="0.500876" />
                        <tangent x="-1.89445e-05" y="0.00147328" z="-0.999999" />
                    </vertex>
                    <vertex>
                        <position x="6.02559" y="117.42" z="-6.60659" />
                        <normal x="0.692953" y="0.226449" z="-0.684498" />
                        <texcoord u="0.0927492" v="0.313363" />
                        <tangent x="-0.702976" y="0.00135396" z="-0.711212" />
                    </vertex>
                    <vertex>
                        <position x="8.53403" y="117.42" z="-0.550679" />
                        <normal x="0.973994" y="0.226497" z="0.00597888" />
                        <texcoord u="0.0628455" v="0.313363" />
                        <tangent x="0.00582349" y="0.00135427" z="-0.999982" />
                    </vertex>
                    <vertex>
                        <position x="6.33818" y="63.298" z="-6.91204" />
                        <normal x="0.707064" y="0.0106692" z="-0.707069" />
                        <texcoord u="0.0927492" v="0.500876" />
                        <tangent x="-0.70712" y="0.00147303" z="-0.707092" />
                    </vertex>
                    <vertex>
                        <position x="-0.0303195" y="117.42" z="-9.11502" />
                        <normal x="0.00597922" y="0.226424" z="-0.97401" />
                        <texcoord u="0.122642" v="0.313363" />
                        <tangent x="-0.995633" y="-0.0893907" z="-0.0268926" />
                    </vertex>
                    <vertex>
                        <position x="-0.0303196" y="63.298" z="-9.54995" />
                        <normal x="-3.36017e-06" y="0.0106783" z="-0.999943" />
                        <texcoord u="0.122642" v="0.500876" />
                        <tangent x="-0.99999" y="-0.00442283" z="-4.38436e-05" />
                    </vertex>
                    <vertex>
                        <position x="-0.0303196" y="63.298" z="-9.54995" />
                        <normal x="-3.36017e-06" y="0.0106783" z="-0.999943" />
                        <texcoord u="0.00308991" v="0.500763" />
                        <tangent x="-0.99999" y="0.00442257" z="5.05615e-05" />
                    </vertex>
                    <vertex>
                        <position x="-6.08623" y="117.42" z="-6.60659" />
                        <normal x="-0.684499" y="0.226437" z="-0.692955" />
                        <texcoord u="0.0329779" v="0.313315" />
                        <tangent x="-0.711212" y="0.00135371" z="0.702976" />
                    </vertex>
                    <vertex>
                        <position x="-0.0303195" y="117.42" z="-9.11502" />
                        <normal x="0.00597922" y="0.226424" z="-0.97401" />
                        <texcoord u="0.00308991" v="0.313315" />
                        <tangent x="-0.995592" y="0.0925217" z="0.0153968" />
                    </vertex>
                    <vertex>
                        <position x="-6.39882" y="63.298" z="-6.91204" />
                        <normal x="-0.707069" y="0.010693" z="-0.707064" />
                        <texcoord u="0.0329779" v="0.500763" />
                        <tangent x="-0.707092" y="0.00147616" z="0.70712" />
                    </vertex>
                    <vertex>
                        <position x="-8.59467" y="117.42" z="-0.550678" />
                        <normal x="-0.973998" y="0.226479" z="-0.00597906" />
                        <texcoord u="0.0628779" v="0.313315" />
                        <tangent x="-0.00582371" y="0.00135412" z="0.999982" />
                    </vertex>
                    <vertex>
                        <position x="-9.03673" y="63.298" z="-0.54354" />
                        <normal x="-0.999943" y="0.0107047" z="3.31716e-06" />
                        <texcoord u="0.0628779" v="0.500763" />
                        <tangent x="1.90505e-05" y="0.00147778" z="0.999999" />
                    </vertex>
                    <vertex>
                        <position x="-6.08623" y="117.42" z="5.50523" />
                        <normal x="-0.69294" y="0.226527" z="0.684485" />
                        <texcoord u="0.0927633" v="0.313315" />
                        <tangent x="0.702977" y="0.00135427" z="0.711212" />
                    </vertex>
                    <vertex>
                        <position x="-6.39881" y="63.298" z="5.82496" />
                        <normal x="-0.707064" y="0.0107066" z="0.707069" />
                        <texcoord u="0.0927633" v="0.500763" />
                        <tangent x="0.70712" y="0.00147804" z="0.707092" />
                    </vertex>
                    <vertex>
                        <position x="-0.030318" y="117.42" z="8.01367" />
                        <normal x="-0.0059788" y="0.226552" z="0.973981" />
                        <texcoord u="0.12266" v="0.313315" />
                        <tangent x="0.995629" y="-0.0894386" z="0.0269152" />
                    </vertex>
                    <vertex>
                        <position x="-0.030318" y="63.298" z="8.46287" />
                        <normal x="3.16125e-06" y="0.0106974" z="0.999943" />
                        <texcoord u="0.12266" v="0.500763" />
                        <tangent x="0.99999" y="-0.00443074" z="4.40426e-05" />
                    </vertex>
                    <vertex>
                        <position x="-0.030318" y="63.298" z="8.46287" />
                        <normal x="3.16125e-06" y="0.0106974" z="0.999943" />
                        <texcoord u="0.00308702" v="0.500876" />
                        <tangent x="0.99999" y="0.00443074" z="-5.03653e-05" />
                    </vertex>
                    <vertex>
                        <position x="6.02559" y="117.42" z="5.50523" />
                        <normal x="0.684483" y="0.226539" z="0.692938" />
                        <texcoord u="0.0329562" v="0.313363" />
                        <tangent x="0.711212" y="0.00135445" z="-0.702977" />
                    </vertex>
                    <vertex>
                        <position x="-0.030318" y="117.42" z="8.01367" />
                        <normal x="-0.0059788" y="0.226552" z="0.973981" />
                        <texcoord u="0.00308702" v="0.313363" />
                        <tangent x="0.995587" y="0.0925711" z="-0.0154207" />
                    </vertex>
                    <vertex>
                        <position x="6.33818" y="63.298" z="5.82495" />
                        <normal x="0.707069" y="0.0106827" z="0.707064" />
                        <texcoord u="0.0329562" v="0.500876" />
                        <tangent x="0.707092" y="0.00147489" z="-0.70712" />
                    </vertex>
                    <vertex>
                        <position x="4.62834" y="121.556" z="-5.20934" />
                        <normal x="0.720547" y="0.427796" z="-0.545713" />
                        <texcoord u="0.0927492" v="0.298228" />
                        <tangent x="-0.603748" y="-2.9465e-08" z="-0.797175" />
                    </vertex>
                    <vertex>
                        <position x="6.55802" y="121.556" z="-0.55068" />
                        <normal x="0.895381" y="0.427796" z="0.123626" />
                        <texcoord u="0.0628455" v="0.298228" />
                        <tangent x="0.136773" y="-1.77532e-07" z="-0.990602" />
                    </vertex>
                    <vertex>
                        <position x="-0.0303194" y="121.556" z="-7.13902" />
                        <normal x="0.123626" y="0.427796" z="-0.895381" />
                        <texcoord u="0.122642" v="0.298228" />
                        <tangent x="-0.977978" y="-0.100376" z="-0.182988" />
                    </vertex>
                    <vertex>
                        <position x="-4.68898" y="121.556" z="-5.20934" />
                        <normal x="-0.545713" y="0.427796" z="-0.720547" />
                        <texcoord u="0.0329779" v="0.298122" />
                        <tangent x="-0.797175" y="-1.80201e-07" z="0.603748" />
                    </vertex>
                    <vertex>
                        <position x="-0.0303194" y="121.556" z="-7.13902" />
                        <normal x="0.123626" y="0.427796" z="-0.895381" />
                        <texcoord u="0.00308991" v="0.298122" />
                        <tangent x="-0.975113" y="0.219714" z="-0.0296593" />
                    </vertex>
                    <vertex>
                        <position x="-6.61866" y="121.556" z="-0.550679" />
                        <normal x="-0.895381" y="0.427796" z="-0.123626" />
                        <texcoord u="0.0628779" v="0.298122" />
                        <tangent x="-0.136773" y="-8.60037e-08" z="0.990602" />
                    </vertex>
                    <vertex>
                        <position x="-4.68898" y="121.556" z="4.10798" />
                        <normal x="-0.720547" y="0.427796" z="0.545713" />
                        <texcoord u="0.0927633" v="0.298122" />
                        <tangent x="0.603748" y="5.02104e-08" z="0.797175" />
                    </vertex>
                    <vertex>
                        <position x="-0.0303182" y="121.556" z="6.03766" />
                        <normal x="-0.123626" y="0.427796" z="0.895381" />
                        <texcoord u="0.12266" v="0.298122" />
                        <tangent x="0.977978" y="-0.100376" z="0.182988" />
                    </vertex>
                    <vertex>
                        <position x="4.62834" y="121.556" z="4.10798" />
                        <normal x="0.545713" y="0.427796" z="0.720547" />
                        <texcoord u="0.0329562" v="0.298228" />
                        <tangent x="0.797175" y="-3.19849e-09" z="-0.603748" />
                    </vertex>
                    <vertex>
                        <position x="-0.0303182" y="121.556" z="6.03766" />
                        <normal x="-0.123626" y="0.427796" z="0.895381" />
                        <texcoord u="0.00308702" v="0.298228" />
                        <tangent x="0.975113" y="0.219715" z="0.0296592" />
                    </vertex>
                </vertexbuffer>
            </geometry>
        </submesh>
        <submesh material="/global/plants/trees/gnarly" usesharedvertices="false" use32bitindexes="false" operationtype="triangle_list">
            <faces count="8">
                <face v1="0" v2="1" v3="2" />
                <face v1="0" v2="2" v3="3" />
                <face v1="4" v2="5" v3="6" />
                <face v1="4" v2="6" v3="7" />
                <face v1="4" v2="7" v3="8" />
                <face v1="4" v2="8" v3="9" />
                <face v1="0" v2="10" v3="11" />
                <face v1="0" v2="11" v3="1" />
            </faces>
            <geometry vertexcount="12">
                <vertexbuffer positions="true" normals="true" texture_coord_dimensions_0="2" tangents="true" texture_coords="1">
                    <vertex>
                        <position x="-0.0303192" y="122.996" z="-0.55068" />
                        <normal x="0" y="1" z="0" />
                        <texcoord u="0.0628613" v="0.290379" />
                        <tangent x="-3.42146e-08" y="0" z="-1" />
                    </vertex>
                    <vertex>
                        <position x="6.55802" y="121.556" z="-0.55068" />
                        <normal x="0.213532" y="0.976936" z="0" />
                        <texcoord u="0.0628455" v="0.298228" />
                        <tangent x="5.08487e-10" y="-1.11142e-10" z="-1" />
                    </vertex>
                    <vertex>
                        <position x="4.62834" y="121.556" z="-5.20934" />
                        <normal x="0.15099" y="0.976936" z="-0.15099" />
                        <texcoord u="0.0927492" v="0.298228" />
                        <tangent x="-0.707107" y="9.4054e-09" z="-0.707107" />
                    </vertex>
                    <vertex>
                        <position x="-0.0303194" y="121.556" z="-7.13902" />
                        <normal x="0" y="0.976936" z="-0.213532" />
                        <texcoord u="0.122642" v="0.298228" />
                        <tangent x="-0.92698" y="-0.0800983" z="-0.36646" />
                    </vertex>
                    <vertex>
                        <position x="-0.0303192" y="122.996" z="-0.55068" />
                        <normal x="0" y="1" z="0" />
                        <texcoord u="0.062862" v="0.290343" />
                        <tangent x="4.56194e-08" y="0" z="1" />
                    </vertex>
                    <vertex>
                        <position x="-0.0303194" y="121.556" z="-7.13902" />
                        <normal x="0" y="0.976936" z="-0.213532" />
                        <texcoord u="0.00308991" v="0.298122" />
                        <tangent x="-0.92698" y="0.0800983" z="0.36646" />
                    </vertex>
                    <vertex>
                        <position x="-4.68898" y="121.556" z="-5.20934" />
                        <normal x="-0.15099" y="0.976936" z="-0.15099" />
                        <texcoord u="0.0329779" v="0.298122" />
                        <tangent x="-0.707107" y="9.15446e-12" z="0.707107" />
                    </vertex>
                    <vertex>
                        <position x="-6.61866" y="121.556" z="-0.550679" />
                        <normal x="-0.213532" y="0.976936" z="0" />
                        <texcoord u="0.0628779" v="0.298122" />
                        <tangent x="7.70093e-08" y="1.68322e-08" z="1" />
                    </vertex>
                    <vertex>
                        <position x="-4.68898" y="121.556" z="4.10798" />
                        <normal x="-0.15099" y="0.976936" z="0.15099" />
                        <texcoord u="0.0927633" v="0.298122" />
                        <tangent x="0.707107" y="9.52569e-09" z="0.707107" />
                    </vertex>
                    <vertex>
                        <position x="-0.0303182" y="121.556" z="6.03766" />
                        <normal x="0" y="0.976936" z="0.213532" />
                        <texcoord u="0.12266" v="0.298122" />
                        <tangent x="0.92698" y="-0.0800983" z="0.36646" />
                    </vertex>
                    <vertex>
                        <position x="-0.0303182" y="121.556" z="6.03766" />
                        <normal x="0" y="0.976936" z="0.213532" />
                        <texcoord u="0.00308702" v="0.298228" />
                        <tangent x="0.92698" y="0.0800984" z="-0.36646" />
                    </vertex>
                    <vertex>
                        <position x="4.62834" y="121.556" z="4.10798" />
                        <normal x="0.15099" y="0.976936" z="0.15099" />
                        <texcoord u="0.0329562" v="0.298228" />
                        <tangent x="0.707107" y="1.89219e-08" z="-0.707107" />
                    </vertex>
                </vertexbuffer>
            </geometry>
        </submesh>
    </submeshes>
</mesh>
